orkestra/__init__.py
orkestra/decorators.py
orkestra/exceptions.py
orkestra/interfaces.py
orkestra/utils.py
orkestra-0.9.4.dist-info/WHEEL
orkestra-0.9.4.dist-info/METADATA
orkestra-0.9.4.dist-info/LICENSE
orkestra-0.9.4.dist-info/RECORD
